{
  "schemaVersion": 1,
  "generatedAt": "2026-07-22T10:58:23.000Z",
  "offers": [
    {
      "id": "muebles-style-spain:KA102710A14",
      "productId": "gtin-04250386024299",
      "merchantId": "muebles-style-spain",
      "merchantProductId": "KA102710A14",
      "country": "ES",
      "currency": "EUR",
      "price": 113,
      "previousPrice": 149,
      "shippingCost": 0,
      "totalPrice": 113,
      "availability": "in_stock",
      "condition": "new",
      "affiliateUrl": "https://www.awin1.com/pclick.php?p=44619259673&a=2996453&m=122118",
      "landingUrl": "https://www.muebles-style.es/products/ka102710a14-manta-de-christian-lacroix-plum-terciopelo?&utm_source=custom&utm_medium=organic&utm_campaign=AWIN%20Spain&utm_content=CHRISTIAN%20LACROIX%20Kuscheldecke%20PLUM%20Velvet",
      "commissionGroup": null,
      "isCommissionable": true,
      "stockQuantity": null,
      "deliveryTime": "1",
      "displayPrice": "EUR113",
      "source": {
        "awProductId": "44619259673",
        "dataFeedId": "112474",
        "awinMerchantId": "122118"
      },
      "lastUpdatedAt": "2026-07-22T10:58:23.000Z"
    },
    {
      "id": "muebles-style-spain:KA102710A15",
      "productId": "gtin-04250386052452",
      "merchantId": "muebles-style-spain",
      "merchantProductId": "KA102710A15",
      "country": "ES",
      "currency": "EUR",
      "price": 102,
      "previousPrice": 139,
      "shippingCost": 0,
      "totalPrice": 102,
      "availability": "in_stock",
      "condition": "new",
      "affiliateUrl": "https://www.awin1.com/pclick.php?p=44619259672&a=2996453&m=122118",
      "landingUrl": "https://www.muebles-style.es/products/ka102710a15-manta-de-christian-lacroix-arabesque-de-terciopelo?&utm_source=custom&utm_medium=organic&utm_campaign=AWIN%20Spain&utm_content=CHRISTIAN%20LACROIX%20Kuscheldecke%20ARABESQUE%20Velvet",
      "commissionGroup": null,
      "isCommissionable": true,
      "stockQuantity": null,
      "deliveryTime": "1",
      "displayPrice": "EUR102",
      "source": {
        "awProductId": "44619259672",
        "dataFeedId": "112474",
        "awinMerchantId": "122118"
      },
      "lastUpdatedAt": "2026-07-22T10:58:23.000Z"
    },
    {
      "id": "muebles-style-spain:KA384033L1",
      "productId": "gtin-04250386100252",
      "merchantId": "muebles-style-spain",
      "merchantProductId": "KA384033L1",
      "country": "ES",
      "currency": "EUR",
      "price": 3709,
      "previousPrice": 7018,
      "shippingCost": 0,
      "totalPrice": 3709,
      "availability": "in_stock",
      "condition": "new",
      "affiliateUrl": "https://www.awin1.com/pclick.php?p=44946795314&a=2996453&m=122118",
      "landingUrl": "https://www.muebles-style.es/products/ka384033l1vk-sofa-kawola-celeste-de-4-plazas-en-piel-color-conac?variant=64905811296605&utm_source=custom&utm_medium=organic&utm_campaign=AWIN%20Spain&utm_content=KAWOLA%20Sofa%20CELESTE%204-Sitzer%20Leder%20cognac",
      "commissionGroup": null,
      "isCommissionable": true,
      "stockQuantity": null,
      "deliveryTime": "5",
      "displayPrice": "EUR3709",
      "source": {
        "awProductId": "44946795314",
        "dataFeedId": "112474",
        "awinMerchantId": "122118"
      },
      "lastUpdatedAt": "2026-07-22T10:58:23.000Z"
    },
    {
      "id": "muebles-style-spain:KA384033L2",
      "productId": "gtin-04250386100269",
      "merchantId": "muebles-style-spain",
      "merchantProductId": "KA384033L2",
      "country": "ES",
      "currency": "EUR",
      "price": 3709,
      "previousPrice": 7018,
      "shippingCost": 0,
      "totalPrice": 3709,
      "availability": "in_stock",
      "condition": "new",
      "affiliateUrl": "https://www.awin1.com/pclick.php?p=44946795307&a=2996453&m=122118",
      "landingUrl": "https://www.muebles-style.es/products/ka384033l2vk-sofa-kawola-celeste-de-4-plazas-en-piel-marron-oscuro?variant=64905811362141&utm_source=custom&utm_medium=organic&utm_campaign=AWIN%20Spain&utm_content=KAWOLA%20Sofa%20CELESTE%204-Sitzer%20Leder%20dunkelbraun",
      "commissionGroup": null,
      "isCommissionable": true,
      "stockQuantity": null,
      "deliveryTime": "5",
      "displayPrice": "EUR3709",
      "source": {
        "awProductId": "44946795307",
        "dataFeedId": "112474",
        "awinMerchantId": "122118"
      },
      "lastUpdatedAt": "2026-07-22T10:58:23.000Z"
    },
    {
      "id": "muebles-style-spain:KA384033L3",
      "productId": "gtin-04250386107732",
      "merchantId": "muebles-style-spain",
      "merchantProductId": "KA384033L3",
      "country": "ES",
      "currency": "EUR",
      "price": 4456,
      "previousPrice": 8437,
      "shippingCost": 0,
      "totalPrice": 4456,
      "availability": "in_stock",
      "condition": "new",
      "affiliateUrl": "https://www.awin1.com/pclick.php?p=44946795315&a=2996453&m=122118",
      "landingUrl": "https://www.muebles-style.es/products/ka384033l1vk-sofa-kawola-celeste-de-4-plazas-en-piel-color-conac?variant=64905811263837&utm_source=custom&utm_medium=organic&utm_campaign=AWIN%20Spain&utm_content=KAWOLA%20Sofa%20CELESTE%204-Sitzer%20Leder%20cognac",
      "commissionGroup": null,
      "isCommissionable": true,
      "stockQuantity": null,
      "deliveryTime": "5",
      "displayPrice": "EUR4456",
      "source": {
        "awProductId": "44946795315",
        "dataFeedId": "112474",
        "awinMerchantId": "122118"
      },
      "lastUpdatedAt": "2026-07-22T10:58:23.000Z"
    },
    {
      "id": "muebles-style-spain:KA384033L4",
      "productId": "gtin-04250386107749",
      "merchantId": "muebles-style-spain",
      "merchantProductId": "KA384033L4",
      "country": "ES",
      "currency": "EUR",
      "price": 4456,
      "previousPrice": 8437,
      "shippingCost": 0,
      "totalPrice": 4456,
      "availability": "in_stock",
      "condition": "new",
      "affiliateUrl": "https://www.awin1.com/pclick.php?p=44946795308&a=2996453&m=122118",
      "landingUrl": "https://www.muebles-style.es/products/ka384033l2vk-sofa-kawola-celeste-de-4-plazas-en-piel-marron-oscuro?variant=64905811394909&utm_source=custom&utm_medium=organic&utm_campaign=AWIN%20Spain&utm_content=KAWOLA%20Sofa%20CELESTE%204-Sitzer%20Leder%20dunkelbraun",
      "commissionGroup": null,
      "isCommissionable": true,
      "stockQuantity": null,
      "deliveryTime": "5",
      "displayPrice": "EUR4456",
      "source": {
        "awProductId": "44946795308",
        "dataFeedId": "112474",
        "awinMerchantId": "122118"
      },
      "lastUpdatedAt": "2026-07-22T10:58:23.000Z"
    },
    {
      "id": "muebles-style-spain:KA384034L1",
      "productId": "gtin-04250386100276",
      "merchantId": "muebles-style-spain",
      "merchantProductId": "KA384034L1",
      "country": "ES",
      "currency": "EUR",
      "price": 3709,
      "previousPrice": 7018,
      "shippingCost": 0,
      "totalPrice": 3709,
      "availability": "in_stock",
      "condition": "new",
      "affiliateUrl": "https://www.awin1.com/pclick.php?p=44946795305&a=2996453&m=122118",
      "landingUrl": "https://www.muebles-style.es/products/ka384034l1vk-sofa-kawola-celeste-de-4-plazas-en-piel-color-camel?variant=64905811099997&utm_source=custom&utm_medium=organic&utm_campaign=AWIN%20Spain&utm_content=KAWOLA%20Sofa%20CELESTE%204-Sitzer%20Leder%20camel",
      "commissionGroup": null,
      "isCommissionable": true,
      "stockQuantity": null,
      "deliveryTime": "5",
      "displayPrice": "EUR3709",
      "source": {
        "awProductId": "44946795305",
        "dataFeedId": "112474",
        "awinMerchantId": "122118"
      },
      "lastUpdatedAt": "2026-07-22T10:58:23.000Z"
    },
    {
      "id": "muebles-style-spain:KA384034L2",
      "productId": "gtin-04250386107763",
      "merchantId": "muebles-style-spain",
      "merchantProductId": "KA384034L2",
      "country": "ES",
      "currency": "EUR",
      "price": 4456,
      "previousPrice": 8437,
      "shippingCost": 0,
      "totalPrice": 4456,
      "availability": "in_stock",
      "condition": "new",
      "affiliateUrl": "https://www.awin1.com/pclick.php?p=44946795306&a=2996453&m=122118",
      "landingUrl": "https://www.muebles-style.es/products/ka384034l1vk-sofa-kawola-celeste-de-4-plazas-en-piel-color-camel?variant=64905811132765&utm_source=custom&utm_medium=organic&utm_campaign=AWIN%20Spain&utm_content=KAWOLA%20Sofa%20CELESTE%204-Sitzer%20Leder%20camel",
      "commissionGroup": null,
      "isCommissionable": true,
      "stockQuantity": null,
      "deliveryTime": "105",
      "displayPrice": "EUR4456",
      "source": {
        "awProductId": "44946795306",
        "dataFeedId": "112474",
        "awinMerchantId": "122118"
      },
      "lastUpdatedAt": "2026-07-22T10:58:23.000Z"
    },
    {
      "id": "muebles-style-spain:KA384035L1",
      "productId": "gtin-04250386100245",
      "merchantId": "muebles-style-spain",
      "merchantProductId": "KA384035L1",
      "country": "ES",
      "currency": "EUR",
      "price": 3709,
      "previousPrice": 7018,
      "shippingCost": 0,
      "totalPrice": 3709,
      "availability": "in_stock",
      "condition": "new",
      "affiliateUrl": "https://www.awin1.com/pclick.php?p=44946795310&a=2996453&m=122118",
      "landingUrl": "https://www.muebles-style.es/products/ka384035l1vk-sofa-kawola-celeste-de-4-plazas-de-cuero-gris?variant=64905811001693&utm_source=custom&utm_medium=organic&utm_campaign=AWIN%20Spain&utm_content=KAWOLA%20Sofa%20CELESTE%204-Sitzer%20Leder%20grau",
      "commissionGroup": null,
      "isCommissionable": true,
      "stockQuantity": null,
      "deliveryTime": "5",
      "displayPrice": "EUR3709",
      "source": {
        "awProductId": "44946795310",
        "dataFeedId": "112474",
        "awinMerchantId": "122118"
      },
      "lastUpdatedAt": "2026-07-22T10:58:23.000Z"
    },
    {
      "id": "muebles-style-spain:KA384035L2",
      "productId": "gtin-04250386091871",
      "merchantId": "muebles-style-spain",
      "merchantProductId": "KA384035L2",
      "country": "ES",
      "currency": "EUR",
      "price": 4456,
      "previousPrice": 8437,
      "shippingCost": 0,
      "totalPrice": 4456,
      "availability": "in_stock",
      "condition": "new",
      "affiliateUrl": "https://www.awin1.com/pclick.php?p=44946795309&a=2996453&m=122118",
      "landingUrl": "https://www.muebles-style.es/products/ka384035l1vk-sofa-kawola-celeste-de-4-plazas-de-cuero-gris?variant=64905810968925&utm_source=custom&utm_medium=organic&utm_campaign=AWIN%20Spain&utm_content=KAWOLA%20Sofa%20CELESTE%204-Sitzer%20Leder%20grau",
      "commissionGroup": null,
      "isCommissionable": true,
      "stockQuantity": null,
      "deliveryTime": "5",
      "displayPrice": "EUR4456",
      "source": {
        "awProductId": "44946795309",
        "dataFeedId": "112474",
        "awinMerchantId": "122118"
      },
      "lastUpdatedAt": "2026-07-22T10:58:23.000Z"
    },
    {
      "id": "muebles-style-spain:KA384413L1",
      "productId": "gtin-04250386100290",
      "merchantId": "muebles-style-spain",
      "merchantProductId": "KA384413L1",
      "country": "ES",
      "currency": "EUR",
      "price": 821,
      "previousPrice": 1503,
      "shippingCost": 0,
      "totalPrice": 821,
      "availability": "in_stock",
      "condition": "new",
      "affiliateUrl": "https://www.awin1.com/pclick.php?p=44946795316&a=2996453&m=122118",
      "landingUrl": "https://www.muebles-style.es/products/ka384413l1-puf-acolchado-kawola-celeste-banco-de-puf-de-cuero-color-conac?&utm_source=custom&utm_medium=organic&utm_campaign=AWIN%20Spain&utm_content=KAWOLA%20Polsterhocker%20CELESTE%20Hockerbank%20Leder%20cognac",
      "commissionGroup": null,
      "isCommissionable": true,
      "stockQuantity": null,
      "deliveryTime": "5",
      "displayPrice": "EUR821",
      "source": {
        "awProductId": "44946795316",
        "dataFeedId": "112474",
        "awinMerchantId": "122118"
      },
      "lastUpdatedAt": "2026-07-22T10:58:23.000Z"
    },
    {
      "id": "muebles-style-spain:KA384413L2",
      "productId": "gtin-04250386100306",
      "merchantId": "muebles-style-spain",
      "merchantProductId": "KA384413L2",
      "country": "ES",
      "currency": "EUR",
      "price": 821,
      "previousPrice": 1503,
      "shippingCost": 0,
      "totalPrice": 821,
      "availability": "in_stock",
      "condition": "new",
      "affiliateUrl": "https://www.awin1.com/pclick.php?p=44946795312&a=2996453&m=122118",
      "landingUrl": "https://www.muebles-style.es/products/ka384413l2-puf-tapizado-kawola-celeste-banco-de-cuero-marron-oscuro?&utm_source=custom&utm_medium=organic&utm_campaign=AWIN%20Spain&utm_content=KAWOLA%20Polsterhocker%20CELESTE%20Hockerbank%20Leder%20dunkelbraun",
      "commissionGroup": null,
      "isCommissionable": true,
      "stockQuantity": null,
      "deliveryTime": "5",
      "displayPrice": "EUR821",
      "source": {
        "awProductId": "44946795312",
        "dataFeedId": "112474",
        "awinMerchantId": "122118"
      },
      "lastUpdatedAt": "2026-07-22T10:58:23.000Z"
    },
    {
      "id": "muebles-style-spain:KA384414L1",
      "productId": "gtin-04250386100313",
      "merchantId": "muebles-style-spain",
      "merchantProductId": "KA384414L1",
      "country": "ES",
      "currency": "EUR",
      "price": 821,
      "previousPrice": 1503,
      "shippingCost": 0,
      "totalPrice": 821,
      "availability": "in_stock",
      "condition": "new",
      "affiliateUrl": "https://www.awin1.com/pclick.php?p=44946795313&a=2996453&m=122118",
      "landingUrl": "https://www.muebles-style.es/products/ka384414l1-puf-tapizado-kawola-celeste-banco-de-cuero-color-camel?&utm_source=custom&utm_medium=organic&utm_campaign=AWIN%20Spain&utm_content=KAWOLA%20Polsterhocker%20CELESTE%20Hockerbank%20Leder%20camel",
      "commissionGroup": null,
      "isCommissionable": true,
      "stockQuantity": null,
      "deliveryTime": "105",
      "displayPrice": "EUR821",
      "source": {
        "awProductId": "44946795313",
        "dataFeedId": "112474",
        "awinMerchantId": "122118"
      },
      "lastUpdatedAt": "2026-07-22T10:58:23.000Z"
    },
    {
      "id": "muebles-style-spain:KA384415L1",
      "productId": "gtin-04250386100283",
      "merchantId": "muebles-style-spain",
      "merchantProductId": "KA384415L1",
      "country": "ES",
      "currency": "EUR",
      "price": 821,
      "previousPrice": 1503,
      "shippingCost": 0,
      "totalPrice": 821,
      "availability": "in_stock",
      "condition": "new",
      "affiliateUrl": "https://www.awin1.com/pclick.php?p=44946795311&a=2996453&m=122118",
      "landingUrl": "https://www.muebles-style.es/products/ka384415l1-kawola-puf-tapizado-celeste-banco-de-cuero-gris?&utm_source=custom&utm_medium=organic&utm_campaign=AWIN%20Spain&utm_content=KAWOLA%20Polsterhocker%20CELESTE%20Hockerbank%20Leder%20grau",
      "commissionGroup": null,
      "isCommissionable": true,
      "stockQuantity": null,
      "deliveryTime": "5",
      "displayPrice": "EUR821",
      "source": {
        "awProductId": "44946795311",
        "dataFeedId": "112474",
        "awinMerchantId": "122118"
      },
      "lastUpdatedAt": "2026-07-22T10:58:23.000Z"
    },
    {
      "id": "muebles-style-spain:KA436403L1",
      "productId": "gtin-04250386104410",
      "merchantId": "muebles-style-spain",
      "merchantProductId": "KA436403L1",
      "country": "ES",
      "currency": "EUR",
      "price": 2287,
      "previousPrice": 3478,
      "shippingCost": 0,
      "totalPrice": 2287,
      "availability": "in_stock",
      "condition": "new",
      "affiliateUrl": "https://www.awin1.com/pclick.php?p=44493732490&a=2996453&m=122118",
      "landingUrl": "https://www.muebles-style.es/products/ka436403l1vk-banco-de-comedor-kawola-eleen-cuero-marron-oscuro?variant=64201416802653&utm_source=custom&utm_medium=organic&utm_campaign=AWIN%20Spain&utm_content=KAWOLA%20Esszimmerbank%20ELEEN%20Leder%20dunkelbraun",
      "commissionGroup": null,
      "isCommissionable": true,
      "stockQuantity": null,
      "deliveryTime": "63",
      "displayPrice": "EUR2287",
      "source": {
        "awProductId": "44493732490",
        "dataFeedId": "112474",
        "awinMerchantId": "122118"
      },
      "lastUpdatedAt": "2026-07-22T10:58:23.000Z"
    },
    {
      "id": "muebles-style-spain:KA436403L13",
      "productId": "gtin-04250386106308",
      "merchantId": "muebles-style-spain",
      "merchantProductId": "KA436403L13",
      "country": "ES",
      "currency": "EUR",
      "price": 1557,
      "previousPrice": 2387,
      "shippingCost": 0,
      "totalPrice": 1557,
      "availability": "in_stock",
      "condition": "new",
      "affiliateUrl": "https://www.awin1.com/pclick.php?p=44493732488&a=2996453&m=122118",
      "landingUrl": "https://www.muebles-style.es/products/ka436403l1vk-banco-de-comedor-kawola-eleen-cuero-marron-oscuro?variant=64201416704349&utm_source=custom&utm_medium=organic&utm_campaign=AWIN%20Spain&utm_content=KAWOLA%20Esszimmerbank%20ELEEN%20Leder%20dunkelbraun",
      "commissionGroup": null,
      "isCommissionable": true,
      "stockQuantity": null,
      "deliveryTime": "63",
      "displayPrice": "EUR1557",
      "source": {
        "awProductId": "44493732488",
        "dataFeedId": "112474",
        "awinMerchantId": "122118"
      },
      "lastUpdatedAt": "2026-07-22T10:58:23.000Z"
    },
    {
      "id": "muebles-style-spain:KA469334F1",
      "productId": "gtin-04250386108678",
      "merchantId": "muebles-style-spain",
      "merchantProductId": "KA469334F1",
      "country": "ES",
      "currency": "EUR",
      "price": 154,
      "previousPrice": 238,
      "shippingCost": 0,
      "totalPrice": 154,
      "availability": "in_stock",
      "condition": "new",
      "affiliateUrl": "https://www.awin1.com/pclick.php?p=45083595051&a=2996453&m=122118",
      "landingUrl": "https://www.muebles-style.es/products/ka469334f1-silla-de-comedor-kawola-lyssia-silla-giratoria-con-tapizado-de-tela-verde?&utm_source=custom&utm_medium=organic&utm_campaign=AWIN%20Spain&utm_content=KAWOLA%20Esszimmerstuhl%20LYSSIA%20Drehstuhl%20Stoff%20gr%C3%BCn",
      "commissionGroup": null,
      "isCommissionable": true,
      "stockQuantity": null,
      "deliveryTime": "8",
      "displayPrice": "EUR154",
      "source": {
        "awProductId": "45083595051",
        "dataFeedId": "112474",
        "awinMerchantId": "122118"
      },
      "lastUpdatedAt": "2026-07-22T10:58:23.000Z"
    },
    {
      "id": "muebles-style-spain:KA469335F1",
      "productId": "gtin-04250386108685",
      "merchantId": "muebles-style-spain",
      "merchantProductId": "KA469335F1",
      "country": "ES",
      "currency": "EUR",
      "price": 154,
      "previousPrice": 238,
      "shippingCost": 0,
      "totalPrice": 154,
      "availability": "in_stock",
      "condition": "new",
      "affiliateUrl": "https://www.awin1.com/pclick.php?p=45083595047&a=2996453&m=122118",
      "landingUrl": "https://www.muebles-style.es/products/ka469335f1-silla-de-comedor-kawola-lyssia-silla-giratoria-con-tapizado-de-tela-gris?&utm_source=custom&utm_medium=organic&utm_campaign=AWIN%20Spain&utm_content=KAWOLA%20Esszimmerstuhl%20LYSSIA%20Drehstuhl%20Stoff%20grau",
      "commissionGroup": null,
      "isCommissionable": true,
      "stockQuantity": null,
      "deliveryTime": "8",
      "displayPrice": "EUR154",
      "source": {
        "awProductId": "45083595047",
        "dataFeedId": "112474",
        "awinMerchantId": "122118"
      },
      "lastUpdatedAt": "2026-07-22T10:58:23.000Z"
    },
    {
      "id": "muebles-style-spain:KA470334F1",
      "productId": "gtin-04250386108692",
      "merchantId": "muebles-style-spain",
      "merchantProductId": "KA470334F1",
      "country": "ES",
      "currency": "EUR",
      "price": 183,
      "previousPrice": 267,
      "shippingCost": 0,
      "totalPrice": 183,
      "availability": "in_stock",
      "condition": "new",
      "affiliateUrl": "https://www.awin1.com/pclick.php?p=45083595054&a=2996453&m=122118",
      "landingUrl": "https://www.muebles-style.es/products/ka470334f1-silla-de-comedor-kawola-edenia-silla-giratoria-con-tapizado-de-tela-verde?&utm_source=custom&utm_medium=organic&utm_campaign=AWIN%20Spain&utm_content=KAWOLA%20Esszimmerstuhl%20EDENIA%20Drehstuhl%20Stoff%20gr%C3%BCn",
      "commissionGroup": null,
      "isCommissionable": true,
      "stockQuantity": null,
      "deliveryTime": "8",
      "displayPrice": "EUR183",
      "source": {
        "awProductId": "45083595054",
        "dataFeedId": "112474",
        "awinMerchantId": "122118"
      },
      "lastUpdatedAt": "2026-07-22T10:58:23.000Z"
    },
    {
      "id": "muebles-style-spain:KA470335F1",
      "productId": "gtin-04250386108708",
      "merchantId": "muebles-style-spain",
      "merchantProductId": "KA470335F1",
      "country": "ES",
      "currency": "EUR",
      "price": 183,
      "previousPrice": 267,
      "shippingCost": 0,
      "totalPrice": 183,
      "availability": "in_stock",
      "condition": "new",
      "affiliateUrl": "https://www.awin1.com/pclick.php?p=45083595050&a=2996453&m=122118",
      "landingUrl": "https://www.muebles-style.es/products/ka470335f1-silla-de-comedor-kawola-edenia-silla-giratoria-con-tapizado-en-tela-gris?&utm_source=custom&utm_medium=organic&utm_campaign=AWIN%20Spain&utm_content=KAWOLA%20Esszimmerstuhl%20EDENIA%20Drehstuhl%20Stoff%20grau",
      "commissionGroup": null,
      "isCommissionable": true,
      "stockQuantity": null,
      "deliveryTime": "8",
      "displayPrice": "EUR183",
      "source": {
        "awProductId": "45083595050",
        "dataFeedId": "112474",
        "awinMerchantId": "122118"
      },
      "lastUpdatedAt": "2026-07-22T10:58:23.000Z"
    },
    {
      "id": "muebles-style-spain:KA471324F1",
      "productId": "gtin-04250386108715",
      "merchantId": "muebles-style-spain",
      "merchantProductId": "KA471324F1",
      "country": "ES",
      "currency": "EUR",
      "price": 196,
      "previousPrice": 283,
      "shippingCost": 0,
      "totalPrice": 196,
      "availability": "in_stock",
      "condition": "new",
      "affiliateUrl": "https://www.awin1.com/pclick.php?p=45083595048&a=2996453&m=122118",
      "landingUrl": "https://www.muebles-style.es/products/ka471324f1-kawola-taburete-de-bar-liliana-taburete-giratorio-de-tela-verde?&utm_source=custom&utm_medium=organic&utm_campaign=AWIN%20Spain&utm_content=KAWOLA%20Barhocker%20LILIANA%20Barstuhl%20drehbar%20Stoff%20gr%C3%BCn",
      "commissionGroup": null,
      "isCommissionable": true,
      "stockQuantity": null,
      "deliveryTime": "8",
      "displayPrice": "EUR196",
      "source": {
        "awProductId": "45083595048",
        "dataFeedId": "112474",
        "awinMerchantId": "122118"
      },
      "lastUpdatedAt": "2026-07-22T10:58:23.000Z"
    },
    {
      "id": "muebles-style-spain:KA471325F1",
      "productId": "gtin-04250386108722",
      "merchantId": "muebles-style-spain",
      "merchantProductId": "KA471325F1",
      "country": "ES",
      "currency": "EUR",
      "price": 196,
      "previousPrice": 283,
      "shippingCost": 0,
      "totalPrice": 196,
      "availability": "in_stock",
      "condition": "new",
      "affiliateUrl": "https://www.awin1.com/pclick.php?p=45083595052&a=2996453&m=122118",
      "landingUrl": "https://www.muebles-style.es/products/ka471325f1-kawola-taburete-de-bar-liliana-taburete-giratorio-de-tela-gris?&utm_source=custom&utm_medium=organic&utm_campaign=AWIN%20Spain&utm_content=KAWOLA%20Barhocker%20LILIANA%20Barstuhl%20drehbar%20Stoff%20grau",
      "commissionGroup": null,
      "isCommissionable": true,
      "stockQuantity": null,
      "deliveryTime": "8",
      "displayPrice": "EUR196",
      "source": {
        "awProductId": "45083595052",
        "dataFeedId": "112474",
        "awinMerchantId": "122118"
      },
      "lastUpdatedAt": "2026-07-22T10:58:23.000Z"
    },
    {
      "id": "muebles-style-spain:KA472330F1",
      "productId": "gtin-04250386108739",
      "merchantId": "muebles-style-spain",
      "merchantProductId": "KA472330F1",
      "country": "ES",
      "currency": "EUR",
      "price": 204,
      "previousPrice": 298,
      "shippingCost": 0,
      "totalPrice": 204,
      "availability": "in_stock",
      "condition": "new",
      "affiliateUrl": "https://www.awin1.com/pclick.php?p=45083595056&a=2996453&m=122118",
      "landingUrl": "https://www.muebles-style.es/products/ka472330f1-silla-de-comedor-kawola-arella-tapizada-en-tela-blanco-crema?&utm_source=custom&utm_medium=organic&utm_campaign=AWIN%20Spain&utm_content=KAWOLA%20Esszimmerstuhl%20ARELLA%20Stoff%20cremewei%C3%9F",
      "commissionGroup": null,
      "isCommissionable": true,
      "stockQuantity": null,
      "deliveryTime": "8",
      "displayPrice": "EUR204",
      "source": {
        "awProductId": "45083595056",
        "dataFeedId": "112474",
        "awinMerchantId": "122118"
      },
      "lastUpdatedAt": "2026-07-22T10:58:23.000Z"
    },
    {
      "id": "muebles-style-spain:KA472334F1",
      "productId": "gtin-04250386108746",
      "merchantId": "muebles-style-spain",
      "merchantProductId": "KA472334F1",
      "country": "ES",
      "currency": "EUR",
      "price": 204,
      "previousPrice": 298,
      "shippingCost": 0,
      "totalPrice": 204,
      "availability": "in_stock",
      "condition": "new",
      "affiliateUrl": "https://www.awin1.com/pclick.php?p=45083595049&a=2996453&m=122118",
      "landingUrl": "https://www.muebles-style.es/products/ka472334f1-silla-de-comedor-kawola-arella-tela-verde?&utm_source=custom&utm_medium=organic&utm_campaign=AWIN%20Spain&utm_content=KAWOLA%20Esszimmerstuhl%20ARELLA%20Stoff%20gr%C3%BCn",
      "commissionGroup": null,
      "isCommissionable": true,
      "stockQuantity": null,
      "deliveryTime": "8",
      "displayPrice": "EUR204",
      "source": {
        "awProductId": "45083595049",
        "dataFeedId": "112474",
        "awinMerchantId": "122118"
      },
      "lastUpdatedAt": "2026-07-22T10:58:23.000Z"
    },
    {
      "id": "muebles-style-spain:KA473334F1",
      "productId": "gtin-04250386108760",
      "merchantId": "muebles-style-spain",
      "merchantProductId": "KA473334F1",
      "country": "ES",
      "currency": "EUR",
      "price": 193,
      "previousPrice": 283,
      "shippingCost": 0,
      "totalPrice": 193,
      "availability": "in_stock",
      "condition": "new",
      "affiliateUrl": "https://www.awin1.com/pclick.php?p=45083595053&a=2996453&m=122118",
      "landingUrl": "https://www.muebles-style.es/products/ka473334f1-silla-de-comedor-kawola-elaria-tela-verde?&utm_source=custom&utm_medium=organic&utm_campaign=AWIN%20Spain&utm_content=KAWOLA%20Esszimmerstuhl%20ELARIA%20Stoff%20gr%C3%BCn",
      "commissionGroup": null,
      "isCommissionable": true,
      "stockQuantity": null,
      "deliveryTime": "13",
      "displayPrice": "EUR193",
      "source": {
        "awProductId": "45083595053",
        "dataFeedId": "112474",
        "awinMerchantId": "122118"
      },
      "lastUpdatedAt": "2026-07-22T10:58:23.000Z"
    },
    {
      "id": "muebles-style-spain:KA473335F1",
      "productId": "gtin-04250386108753",
      "merchantId": "muebles-style-spain",
      "merchantProductId": "KA473335F1",
      "country": "ES",
      "currency": "EUR",
      "price": 193,
      "previousPrice": 283,
      "shippingCost": 0,
      "totalPrice": 193,
      "availability": "in_stock",
      "condition": "new",
      "affiliateUrl": "https://www.awin1.com/pclick.php?p=45083595055&a=2996453&m=122118",
      "landingUrl": "https://www.muebles-style.es/products/ka473335f1-silla-de-comedor-kawola-elaria-tela-gris-claro?&utm_source=custom&utm_medium=organic&utm_campaign=AWIN%20Spain&utm_content=KAWOLA%20Esszimmerstuhl%20ELARIA%20Stoff%20hellgrau",
      "commissionGroup": null,
      "isCommissionable": true,
      "stockQuantity": null,
      "deliveryTime": "8",
      "displayPrice": "EUR193",
      "source": {
        "awProductId": "45083595055",
        "dataFeedId": "112474",
        "awinMerchantId": "122118"
      },
      "lastUpdatedAt": "2026-07-22T10:58:23.000Z"
    },
    {
      "id": "muebles-style-spain:KA475350P1",
      "productId": "gtin-04250386108173",
      "merchantId": "muebles-style-spain",
      "merchantProductId": "KA475350P1",
      "country": "ES",
      "currency": "EUR",
      "price": 90,
      "previousPrice": 125,
      "shippingCost": 0,
      "totalPrice": 90,
      "availability": "in_stock",
      "condition": "new",
      "affiliateUrl": "https://www.awin1.com/pclick.php?p=44493732487&a=2996453&m=122118",
      "landingUrl": "https://www.muebles-style.es/products/ka475350p1-silla-de-jardin-kawola-altea-de-exterior-de-plastico-beige-con-cojin?&utm_source=custom&utm_medium=organic&utm_campaign=AWIN%20Spain&utm_content=KAWOLA%20Gartenstuhl%20ALTEA%20Outdoor%20Kunststoff%20beige%20mit%20Kissen",
      "commissionGroup": null,
      "isCommissionable": true,
      "stockQuantity": null,
      "deliveryTime": "1",
      "displayPrice": "EUR90",
      "source": {
        "awProductId": "44493732487",
        "dataFeedId": "112474",
        "awinMerchantId": "122118"
      },
      "lastUpdatedAt": "2026-07-22T10:58:23.000Z"
    },
    {
      "id": "muebles-style-spain:KA480030F1",
      "productId": "gtin-04250386107848",
      "merchantId": "muebles-style-spain",
      "merchantProductId": "KA480030F1",
      "country": "ES",
      "currency": "EUR",
      "price": 3032,
      "previousPrice": 4625,
      "shippingCost": 0,
      "totalPrice": 3032,
      "availability": "in_stock",
      "condition": "new",
      "affiliateUrl": "https://www.awin1.com/pclick.php?p=44853585361&a=2996453&m=122118",
      "landingUrl": "https://www.muebles-style.es/products/ka480030f1vk-sofa-funcional-kawola-holly-de-2-plazas-en-tela-blanca?variant=64807603732829&utm_source=custom&utm_medium=organic&utm_campaign=AWIN%20Spain&utm_content=KAWOLA%20Funktionssofa%20HOLLY%202-Sitzer%20Stoff%20wei%C3%9F",
      "commissionGroup": null,
      "isCommissionable": true,
      "stockQuantity": null,
      "deliveryTime": "63",
      "displayPrice": "EUR3032",
      "source": {
        "awProductId": "44853585361",
        "dataFeedId": "112474",
        "awinMerchantId": "122118"
      },
      "lastUpdatedAt": "2026-07-22T10:58:23.000Z"
    },
    {
      "id": "muebles-style-spain:KA480030F2",
      "productId": "gtin-04250386107893",
      "merchantId": "muebles-style-spain",
      "merchantProductId": "KA480030F2",
      "country": "ES",
      "currency": "EUR",
      "price": 2858,
      "previousPrice": 4348,
      "shippingCost": 0,
      "totalPrice": 2858,
      "availability": "in_stock",
      "condition": "new",
      "affiliateUrl": "https://www.awin1.com/pclick.php?p=44864397545&a=2996453&m=122118",
      "landingUrl": "https://www.muebles-style.es/products/ka480030f1vk-sofa-funcional-kawola-holly-de-2-plazas-en-tela-blanca?variant=64807603765597&utm_source=custom&utm_medium=organic&utm_campaign=AWIN%20Spain&utm_content=KAWOLA%20Funktionssofa%20HOLLY%202-Sitzer%20Stoff%20wei%C3%9F",
      "commissionGroup": null,
      "isCommissionable": true,
      "stockQuantity": null,
      "deliveryTime": "63",
      "displayPrice": "EUR2858",
      "source": {
        "awProductId": "44864397545",
        "dataFeedId": "112474",
        "awinMerchantId": "122118"
      },
      "lastUpdatedAt": "2026-07-22T10:58:23.000Z"
    },
    {
      "id": "muebles-style-spain:KA480030F3",
      "productId": "gtin-04250386107947",
      "merchantId": "muebles-style-spain",
      "merchantProductId": "KA480030F3",
      "country": "ES",
      "currency": "EUR",
      "price": 2660,
      "previousPrice": 4029,
      "shippingCost": 0,
      "totalPrice": 2660,
      "availability": "in_stock",
      "condition": "new",
      "affiliateUrl": "https://www.awin1.com/pclick.php?p=44864397546&a=2996453&m=122118",
      "landingUrl": "https://www.muebles-style.es/products/ka480030f1vk-sofa-funcional-kawola-holly-de-2-plazas-en-tela-blanca?variant=64815735767389&utm_source=custom&utm_medium=organic&utm_campaign=AWIN%20Spain&utm_content=KAWOLA%20Funktionssofa%20HOLLY%202-Sitzer%20Stoff%20wei%C3%9F",
      "commissionGroup": null,
      "isCommissionable": true,
      "stockQuantity": null,
      "deliveryTime": "63",
      "displayPrice": "EUR2660",
      "source": {
        "awProductId": "44864397546",
        "dataFeedId": "112474",
        "awinMerchantId": "122118"
      },
      "lastUpdatedAt": "2026-07-22T10:58:23.000Z"
    },
    {
      "id": "muebles-style-spain:KA480033F1",
      "productId": "gtin-04250386107831",
      "merchantId": "muebles-style-spain",
      "merchantProductId": "KA480033F1",
      "country": "ES",
      "currency": "EUR",
      "price": 3032,
      "previousPrice": 4625,
      "shippingCost": 0,
      "totalPrice": 3032,
      "availability": "in_stock",
      "condition": "new",
      "affiliateUrl": "https://www.awin1.com/pclick.php?p=44853585360&a=2996453&m=122118",
      "landingUrl": "https://www.muebles-style.es/products/ka480033f1vk-sofa-funcional-kawola-holly-de-2-plazas-en-tela-color-conac?variant=64807605371229&utm_source=custom&utm_medium=organic&utm_campaign=AWIN%20Spain&utm_content=KAWOLA%20Funktionssofa%20HOLLY%202-Sitzer%20Stoff%20cognac",
      "commissionGroup": null,
      "isCommissionable": true,
      "stockQuantity": null,
      "deliveryTime": "63",
      "displayPrice": "EUR3032",
      "source": {
        "awProductId": "44853585360",
        "dataFeedId": "112474",
        "awinMerchantId": "122118"
      },
      "lastUpdatedAt": "2026-07-22T10:58:23.000Z"
    },
    {
      "id": "muebles-style-spain:KA480033F2",
      "productId": "gtin-04250386107886",
      "merchantId": "muebles-style-spain",
      "merchantProductId": "KA480033F2",
      "country": "ES",
      "currency": "EUR",
      "price": 2858,
      "previousPrice": 4348,
      "shippingCost": 0,
      "totalPrice": 2858,
      "availability": "in_stock",
      "condition": "new",
      "affiliateUrl": "https://www.awin1.com/pclick.php?p=44864397543&a=2996453&m=122118",
      "landingUrl": "https://www.muebles-style.es/products/ka480033f1vk-sofa-funcional-kawola-holly-de-2-plazas-en-tela-color-conac?variant=64807605403997&utm_source=custom&utm_medium=organic&utm_campaign=AWIN%20Spain&utm_content=KAWOLA%20Funktionssofa%20HOLLY%202-Sitzer%20Stoff%20cognac",
      "commissionGroup": null,
      "isCommissionable": true,
      "stockQuantity": null,
      "deliveryTime": "63",
      "displayPrice": "EUR2858",
      "source": {
        "awProductId": "44864397543",
        "dataFeedId": "112474",
        "awinMerchantId": "122118"
      },
      "lastUpdatedAt": "2026-07-22T10:58:23.000Z"
    },
    {
      "id": "muebles-style-spain:KA480033F3",
      "productId": "gtin-04250386107930",
      "merchantId": "muebles-style-spain",
      "merchantProductId": "KA480033F3",
      "country": "ES",
      "currency": "EUR",
      "price": 2660,
      "previousPrice": 4029,
      "shippingCost": 0,
      "totalPrice": 2660,
      "availability": "in_stock",
      "condition": "new",
      "affiliateUrl": "https://www.awin1.com/pclick.php?p=44864397544&a=2996453&m=122118",
      "landingUrl": "https://www.muebles-style.es/products/ka480033f1vk-sofa-funcional-kawola-holly-de-2-plazas-en-tela-color-conac?variant=64815736324445&utm_source=custom&utm_medium=organic&utm_campaign=AWIN%20Spain&utm_content=KAWOLA%20Funktionssofa%20HOLLY%202-Sitzer%20Stoff%20cognac",
      "commissionGroup": null,
      "isCommissionable": true,
      "stockQuantity": null,
      "deliveryTime": "63",
      "displayPrice": "EUR2660",
      "source": {
        "awProductId": "44864397544",
        "dataFeedId": "112474",
        "awinMerchantId": "122118"
      },
      "lastUpdatedAt": "2026-07-22T10:58:23.000Z"
    },
    {
      "id": "muebles-style-spain:KA480035F1",
      "productId": "gtin-04250386107824",
      "merchantId": "muebles-style-spain",
      "merchantProductId": "KA480035F1",
      "country": "ES",
      "currency": "EUR",
      "price": 3032,
      "previousPrice": 4625,
      "shippingCost": 0,
      "totalPrice": 3032,
      "availability": "in_stock",
      "condition": "new",
      "affiliateUrl": "https://www.awin1.com/pclick.php?p=44853585363&a=2996453&m=122118",
      "landingUrl": "https://www.muebles-style.es/products/ka480035f1vk-sofa-funcional-kawola-holly-de-2-plazas-tapizado-en-tela-antracita?variant=64807609074013&utm_source=custom&utm_medium=organic&utm_campaign=AWIN%20Spain&utm_content=KAWOLA%20Funktionssofa%20HOLLY%202-Sitzer%20Stoff%20anthrazit",
      "commissionGroup": null,
      "isCommissionable": true,
      "stockQuantity": null,
      "deliveryTime": "63",
      "displayPrice": "EUR3032",
      "source": {
        "awProductId": "44853585363",
        "dataFeedId": "112474",
        "awinMerchantId": "122118"
      },
      "lastUpdatedAt": "2026-07-22T10:58:23.000Z"
    },
    {
      "id": "muebles-style-spain:KA480035F2",
      "productId": "gtin-04250386107855",
      "merchantId": "muebles-style-spain",
      "merchantProductId": "KA480035F2",
      "country": "ES",
      "currency": "EUR",
      "price": 3032,
      "previousPrice": 4625,
      "shippingCost": 0,
      "totalPrice": 3032,
      "availability": "in_stock",
      "condition": "new",
      "affiliateUrl": "https://www.awin1.com/pclick.php?p=44853585359&a=2996453&m=122118",
      "landingUrl": "https://www.muebles-style.es/products/ka480035f2vk-sofa-funcional-kawola-holly-de-2-plazas-de-tela-gris?variant=64807606518109&utm_source=custom&utm_medium=organic&utm_campaign=AWIN%20Spain&utm_content=KAWOLA%20Funktionssofa%20HOLLY%202-Sitzer%20Stoff%20grau",
      "commissionGroup": null,
      "isCommissionable": true,
      "stockQuantity": null,
      "deliveryTime": "63",
      "displayPrice": "EUR3032",
      "source": {
        "awProductId": "44853585359",
        "dataFeedId": "112474",
        "awinMerchantId": "122118"
      },
      "lastUpdatedAt": "2026-07-22T10:58:23.000Z"
    },
    {
      "id": "muebles-style-spain:KA480035F3",
      "productId": "gtin-04250386107879",
      "merchantId": "muebles-style-spain",
      "merchantProductId": "KA480035F3",
      "country": "ES",
      "currency": "EUR",
      "price": 2858,
      "previousPrice": 4348,
      "shippingCost": 0,
      "totalPrice": 2858,
      "availability": "in_stock",
      "condition": "new",
      "affiliateUrl": "https://www.awin1.com/pclick.php?p=44864397550&a=2996453&m=122118",
      "landingUrl": "https://www.muebles-style.es/products/ka480035f1vk-sofa-funcional-kawola-holly-de-2-plazas-tapizado-en-tela-antracita?variant=64807609106781&utm_source=custom&utm_medium=organic&utm_campaign=AWIN%20Spain&utm_content=KAWOLA%20Funktionssofa%20HOLLY%202-Sitzer%20Stoff%20anthrazit",
      "commissionGroup": null,
      "isCommissionable": true,
      "stockQuantity": null,
      "deliveryTime": "63",
      "displayPrice": "EUR2858",
      "source": {
        "awProductId": "44864397550",
        "dataFeedId": "112474",
        "awinMerchantId": "122118"
      },
      "lastUpdatedAt": "2026-07-22T10:58:23.000Z"
    },
    {
      "id": "muebles-style-spain:KA480035F4",
      "productId": "gtin-04250386107909",
      "merchantId": "muebles-style-spain",
      "merchantProductId": "KA480035F4",
      "country": "ES",
      "currency": "EUR",
      "price": 2858,
      "previousPrice": 4348,
      "shippingCost": 0,
      "totalPrice": 2858,
      "availability": "in_stock",
      "condition": "new",
      "affiliateUrl": "https://www.awin1.com/pclick.php?p=44864397542&a=2996453&m=122118",
      "landingUrl": "https://www.muebles-style.es/products/ka480035f2vk-sofa-funcional-kawola-holly-de-2-plazas-de-tela-gris?variant=64807606550877&utm_source=custom&utm_medium=organic&utm_campaign=AWIN%20Spain&utm_content=KAWOLA%20Funktionssofa%20HOLLY%202-Sitzer%20Stoff%20grau",
      "commissionGroup": null,
      "isCommissionable": true,
      "stockQuantity": null,
      "deliveryTime": "63",
      "displayPrice": "EUR2858",
      "source": {
        "awProductId": "44864397542",
        "dataFeedId": "112474",
        "awinMerchantId": "122118"
      },
      "lastUpdatedAt": "2026-07-22T10:58:23.000Z"
    },
    {
      "id": "muebles-style-spain:KA480035F5",
      "productId": "gtin-04250386107923",
      "merchantId": "muebles-style-spain",
      "merchantProductId": "KA480035F5",
      "country": "ES",
      "currency": "EUR",
      "price": 2660,
      "previousPrice": 4029,
      "shippingCost": 0,
      "totalPrice": 2660,
      "availability": "in_stock",
      "condition": "new",
      "affiliateUrl": "https://www.awin1.com/pclick.php?p=44864397549&a=2996453&m=122118",
      "landingUrl": "https://www.muebles-style.es/products/ka480035f1vk-sofa-funcional-kawola-holly-de-2-plazas-tapizado-en-tela-antracita?variant=64807609139549&utm_source=custom&utm_medium=organic&utm_campaign=AWIN%20Spain&utm_content=KAWOLA%20Funktionssofa%20HOLLY%202-Sitzer%20Stoff%20anthrazit",
      "commissionGroup": null,
      "isCommissionable": true,
      "stockQuantity": null,
      "deliveryTime": "63",
      "displayPrice": "EUR2660",
      "source": {
        "awProductId": "44864397549",
        "dataFeedId": "112474",
        "awinMerchantId": "122118"
      },
      "lastUpdatedAt": "2026-07-22T10:58:23.000Z"
    },
    {
      "id": "muebles-style-spain:KA480035F6",
      "productId": "gtin-04250386107954",
      "merchantId": "muebles-style-spain",
      "merchantProductId": "KA480035F6",
      "country": "ES",
      "currency": "EUR",
      "price": 2660,
      "previousPrice": 4029,
      "shippingCost": 0,
      "totalPrice": 2660,
      "availability": "in_stock",
      "condition": "new",
      "affiliateUrl": "https://www.awin1.com/pclick.php?p=44864397541&a=2996453&m=122118",
      "landingUrl": "https://www.muebles-style.es/products/ka480035f2vk-sofa-funcional-kawola-holly-de-2-plazas-de-tela-gris?variant=64807606583645&utm_source=custom&utm_medium=organic&utm_campaign=AWIN%20Spain&utm_content=KAWOLA%20Funktionssofa%20HOLLY%202-Sitzer%20Stoff%20grau",
      "commissionGroup": null,
      "isCommissionable": true,
      "stockQuantity": null,
      "deliveryTime": "63",
      "displayPrice": "EUR2660",
      "source": {
        "awProductId": "44864397541",
        "dataFeedId": "112474",
        "awinMerchantId": "122118"
      },
      "lastUpdatedAt": "2026-07-22T10:58:23.000Z"
    },
    {
      "id": "muebles-style-spain:KA480036F1",
      "productId": "gtin-04250386107817",
      "merchantId": "muebles-style-spain",
      "merchantProductId": "KA480036F1",
      "country": "ES",
      "currency": "EUR",
      "price": 3032,
      "previousPrice": 4625,
      "shippingCost": 0,
      "totalPrice": 3032,
      "availability": "in_stock",
      "condition": "new",
      "affiliateUrl": "https://www.awin1.com/pclick.php?p=44853585362&a=2996453&m=122118",
      "landingUrl": "https://www.muebles-style.es/products/ka480036f1vk-sofa-funcional-kawola-holly-de-2-plazas-tela-color-mostaza?variant=64807611892061&utm_source=custom&utm_medium=organic&utm_campaign=AWIN%20Spain&utm_content=KAWOLA%20Funktionssofa%20HOLLY%202-Sitzer%20Stoff%20senf",
      "commissionGroup": null,
      "isCommissionable": true,
      "stockQuantity": null,
      "deliveryTime": "63",
      "displayPrice": "EUR3032",
      "source": {
        "awProductId": "44853585362",
        "dataFeedId": "112474",
        "awinMerchantId": "122118"
      },
      "lastUpdatedAt": "2026-07-22T10:58:23.000Z"
    },
    {
      "id": "muebles-style-spain:KA480036F2",
      "productId": "gtin-04250386107862",
      "merchantId": "muebles-style-spain",
      "merchantProductId": "KA480036F2",
      "country": "ES",
      "currency": "EUR",
      "price": 2858,
      "previousPrice": 4348,
      "shippingCost": 0,
      "totalPrice": 2858,
      "availability": "in_stock",
      "condition": "new",
      "affiliateUrl": "https://www.awin1.com/pclick.php?p=44864397548&a=2996453&m=122118",
      "landingUrl": "https://www.muebles-style.es/products/ka480036f1vk-sofa-funcional-kawola-holly-de-2-plazas-tela-color-mostaza?variant=64807611924829&utm_source=custom&utm_medium=organic&utm_campaign=AWIN%20Spain&utm_content=KAWOLA%20Funktionssofa%20HOLLY%202-Sitzer%20Stoff%20senf",
      "commissionGroup": null,
      "isCommissionable": true,
      "stockQuantity": null,
      "deliveryTime": "63",
      "displayPrice": "EUR2858",
      "source": {
        "awProductId": "44864397548",
        "dataFeedId": "112474",
        "awinMerchantId": "122118"
      },
      "lastUpdatedAt": "2026-07-22T10:58:23.000Z"
    },
    {
      "id": "muebles-style-spain:KA480036F3",
      "productId": "gtin-04250386107916",
      "merchantId": "muebles-style-spain",
      "merchantProductId": "KA480036F3",
      "country": "ES",
      "currency": "EUR",
      "price": 2660,
      "previousPrice": 4029,
      "shippingCost": 0,
      "totalPrice": 2660,
      "availability": "in_stock",
      "condition": "new",
      "affiliateUrl": "https://www.awin1.com/pclick.php?p=44864397547&a=2996453&m=122118",
      "landingUrl": "https://www.muebles-style.es/products/ka480036f1vk-sofa-funcional-kawola-holly-de-2-plazas-tela-color-mostaza?variant=64807611859293&utm_source=custom&utm_medium=organic&utm_campaign=AWIN%20Spain&utm_content=KAWOLA%20Funktionssofa%20HOLLY%202-Sitzer%20Stoff%20senf",
      "commissionGroup": null,
      "isCommissionable": true,
      "stockQuantity": null,
      "deliveryTime": "63",
      "displayPrice": "EUR2660",
      "source": {
        "awProductId": "44864397547",
        "dataFeedId": "112474",
        "awinMerchantId": "122118"
      },
      "lastUpdatedAt": "2026-07-22T10:58:23.000Z"
    },
    {
      "id": "muebles-style-spain:KAB74634671",
      "productId": "gtin-04250386108197",
      "merchantId": "muebles-style-spain",
      "merchantProductId": "KAB74634671",
      "country": "ES",
      "currency": "EUR",
      "price": 968,
      "previousPrice": 1420,
      "shippingCost": 0,
      "totalPrice": 968,
      "availability": "in_stock",
      "condition": "new",
      "affiliateUrl": "https://www.awin1.com/pclick.php?p=44504518084&a=2996453&m=122118",
      "landingUrl": "https://www.muebles-style.es/products/kab74634671vk-conjunto-de-muebles-de-jardin-kawola-miava-7-piezas-color-crema?variant=64214067511645&utm_source=custom&utm_medium=organic&utm_campaign=AWIN%20Spain&utm_content=KAWOLA%20Gartenm%C3%B6bel%20Set%20MIAVA%207-tlg.%20cremefarben",
      "commissionGroup": null,
      "isCommissionable": true,
      "stockQuantity": null,
      "deliveryTime": "5",
      "displayPrice": "EUR968",
      "source": {
        "awProductId": "44504518084",
        "dataFeedId": "112474",
        "awinMerchantId": "122118"
      },
      "lastUpdatedAt": "2026-07-22T10:58:23.000Z"
    },
    {
      "id": "muebles-style-spain:KAB74634672",
      "productId": "gtin-04250386108203",
      "merchantId": "muebles-style-spain",
      "merchantProductId": "KAB74634672",
      "country": "ES",
      "currency": "EUR",
      "price": 968,
      "previousPrice": 1470,
      "shippingCost": 0,
      "totalPrice": 968,
      "availability": "in_stock",
      "condition": "new",
      "affiliateUrl": "https://www.awin1.com/pclick.php?p=44504518083&a=2996453&m=122118",
      "landingUrl": "https://www.muebles-style.es/products/kab74634671vk-conjunto-de-muebles-de-jardin-kawola-miava-7-piezas-color-crema?variant=64214067544413&utm_source=custom&utm_medium=organic&utm_campaign=AWIN%20Spain&utm_content=KAWOLA%20Gartenm%C3%B6bel%20Set%20MIAVA%207-tlg.%20cremefarben",
      "commissionGroup": null,
      "isCommissionable": true,
      "stockQuantity": null,
      "deliveryTime": "5",
      "displayPrice": "EUR968",
      "source": {
        "awProductId": "44504518083",
        "dataFeedId": "112474",
        "awinMerchantId": "122118"
      },
      "lastUpdatedAt": "2026-07-22T10:58:23.000Z"
    },
    {
      "id": "muebles-style-spain:KAB74644672",
      "productId": "gtin-04250386108227",
      "merchantId": "muebles-style-spain",
      "merchantProductId": "KAB74644672",
      "country": "ES",
      "currency": "EUR",
      "price": 1710,
      "previousPrice": 2655,
      "shippingCost": 0,
      "totalPrice": 1710,
      "availability": "in_stock",
      "condition": "new",
      "affiliateUrl": "https://www.awin1.com/pclick.php?p=44504518080&a=2996453&m=122118",
      "landingUrl": "https://www.muebles-style.es/products/kab74644672-conjunto-de-muebles-de-jardin-kawola-lusha-7-piezas-acero-color-turquesa?&utm_source=custom&utm_medium=organic&utm_campaign=AWIN%20Spain&utm_content=KAWOLA%20Gartenm%C3%B6bel%20Set%20LUSHA%207-tlg.%20Stahl%20t%C3%BCrkis",
      "commissionGroup": null,
      "isCommissionable": true,
      "stockQuantity": null,
      "deliveryTime": "5",
      "displayPrice": "EUR1710",
      "source": {
        "awProductId": "44504518080",
        "dataFeedId": "112474",
        "awinMerchantId": "122118"
      },
      "lastUpdatedAt": "2026-07-22T10:58:23.000Z"
    },
    {
      "id": "muebles-style-spain:KAB74644673",
      "productId": "gtin-04250386108234",
      "merchantId": "muebles-style-spain",
      "merchantProductId": "KAB74644673",
      "country": "ES",
      "currency": "EUR",
      "price": 1710,
      "previousPrice": 2655,
      "shippingCost": 0,
      "totalPrice": 1710,
      "availability": "in_stock",
      "condition": "new",
      "affiliateUrl": "https://www.awin1.com/pclick.php?p=44504518076&a=2996453&m=122118",
      "landingUrl": "https://www.muebles-style.es/products/kab74644673-conjunto-de-muebles-de-jardin-kawola-lusha-7-piezas-acero-gris-oscuro?&utm_source=custom&utm_medium=organic&utm_campaign=AWIN%20Spain&utm_content=KAWOLA%20Gartenm%C3%B6bel%20Set%20LUSHA%207-tlg.%20Stahl%20dunkelgrau",
      "commissionGroup": null,
      "isCommissionable": true,
      "stockQuantity": null,
      "deliveryTime": "5",
      "displayPrice": "EUR1710",
      "source": {
        "awProductId": "44504518076",
        "dataFeedId": "112474",
        "awinMerchantId": "122118"
      },
      "lastUpdatedAt": "2026-07-22T10:58:23.000Z"
    },
    {
      "id": "muebles-style-spain:KAB74654671",
      "productId": "gtin-04250386108241",
      "merchantId": "muebles-style-spain",
      "merchantProductId": "KAB74654671",
      "country": "ES",
      "currency": "EUR",
      "price": 1987,
      "previousPrice": 2769,
      "shippingCost": 0,
      "totalPrice": 1987,
      "availability": "in_stock",
      "condition": "new",
      "affiliateUrl": "https://www.awin1.com/pclick.php?p=44504518077&a=2996453&m=122118",
      "landingUrl": "https://www.muebles-style.es/products/kab74654671-conjunto-de-muebles-de-jardin-kawola-amur-7-piezas-aluminio-color-crema?&utm_source=custom&utm_medium=organic&utm_campaign=AWIN%20Spain&utm_content=KAWOLA%20Gartenm%C3%B6bel%20Set%20AMUR%207-tlg.%20Aluminium%20cremefarben",
      "commissionGroup": null,
      "isCommissionable": true,
      "stockQuantity": null,
      "deliveryTime": "5",
      "displayPrice": "EUR1987",
      "source": {
        "awProductId": "44504518077",
        "dataFeedId": "112474",
        "awinMerchantId": "122118"
      },
      "lastUpdatedAt": "2026-07-22T10:58:23.000Z"
    },
    {
      "id": "muebles-style-spain:KAB74654672",
      "productId": "gtin-04250386108258",
      "merchantId": "muebles-style-spain",
      "merchantProductId": "KAB74654672",
      "country": "ES",
      "currency": "EUR",
      "price": 1987,
      "previousPrice": 2769,
      "shippingCost": 0,
      "totalPrice": 1987,
      "availability": "in_stock",
      "condition": "new",
      "affiliateUrl": "https://www.awin1.com/pclick.php?p=44504518078&a=2996453&m=122118",
      "landingUrl": "https://www.muebles-style.es/products/kab74654672-conjunto-de-muebles-de-jardin-kawola-amur-7-piezas-aluminio-gris?&utm_source=custom&utm_medium=organic&utm_campaign=AWIN%20Spain&utm_content=KAWOLA%20Gartenm%C3%B6bel%20Set%20AMUR%207-tlg.%20Aluminium%20grau",
      "commissionGroup": null,
      "isCommissionable": true,
      "stockQuantity": null,
      "deliveryTime": "5",
      "displayPrice": "EUR1987",
      "source": {
        "awProductId": "44504518078",
        "dataFeedId": "112474",
        "awinMerchantId": "122118"
      },
      "lastUpdatedAt": "2026-07-22T10:58:23.000Z"
    },
    {
      "id": "muebles-style-spain:KAB74664671",
      "productId": "gtin-04250386108265",
      "merchantId": "muebles-style-spain",
      "merchantProductId": "KAB74664671",
      "country": "ES",
      "currency": "EUR",
      "price": 1808,
      "previousPrice": 2593,
      "shippingCost": 0,
      "totalPrice": 1808,
      "availability": "in_stock",
      "condition": "new",
      "affiliateUrl": "https://www.awin1.com/pclick.php?p=44504518081&a=2996453&m=122118",
      "landingUrl": "https://www.muebles-style.es/products/kab74664671-conjunto-de-muebles-de-jardin-kawola-indus-7-piezas-aluminio-color-crema?&utm_source=custom&utm_medium=organic&utm_campaign=AWIN%20Spain&utm_content=KAWOLA%20Gartenm%C3%B6bel%20Set%20INDUS%207-tlg.%20Aluminium%20cremefarben",
      "commissionGroup": null,
      "isCommissionable": true,
      "stockQuantity": null,
      "deliveryTime": "5",
      "displayPrice": "EUR1808",
      "source": {
        "awProductId": "44504518081",
        "dataFeedId": "112474",
        "awinMerchantId": "122118"
      },
      "lastUpdatedAt": "2026-07-22T10:58:23.000Z"
    },
    {
      "id": "muebles-style-spain:KAB74664672",
      "productId": "gtin-04250386108272",
      "merchantId": "muebles-style-spain",
      "merchantProductId": "KAB74664672",
      "country": "ES",
      "currency": "EUR",
      "price": 1808,
      "previousPrice": 2593,
      "shippingCost": 0,
      "totalPrice": 1808,
      "availability": "in_stock",
      "condition": "new",
      "affiliateUrl": "https://www.awin1.com/pclick.php?p=44504518082&a=2996453&m=122118",
      "landingUrl": "https://www.muebles-style.es/products/kab74664672-conjunto-de-muebles-de-jardin-kawola-indus-7-piezas-aluminio-gris?&utm_source=custom&utm_medium=organic&utm_campaign=AWIN%20Spain&utm_content=KAWOLA%20Gartenm%C3%B6bel%20Set%20INDUS%207-tlg.%20Aluminium%20grau",
      "commissionGroup": null,
      "isCommissionable": true,
      "stockQuantity": null,
      "deliveryTime": "5",
      "displayPrice": "EUR1808",
      "source": {
        "awProductId": "44504518082",
        "dataFeedId": "112474",
        "awinMerchantId": "122118"
      },
      "lastUpdatedAt": "2026-07-22T10:58:23.000Z"
    }
  ]
}
